saleStorePredictor/__init__.py
saleStorePredictor/components/__init__.py
saleStorePredictor/components/data_ingestion.py
saleStorePredictor/components/data_preprocessing.py
saleStorePredictor/components/data_validation.py
saleStorePredictor/components/model_evaluation_pusher.py
saleStorePredictor/components/model_training.py
saleStorePredictor/config/__init__.py
saleStorePredictor/config/configuration.py
saleStorePredictor/constants/__init__.py
saleStorePredictor/entity/__init__.py
saleStorePredictor/entity/artifact_entity.py
saleStorePredictor/entity/config_entity.py
saleStorePredictor/entity/model_factory.py
saleStorePredictor/pipeline/__init__.py
saleStorePredictor/pipeline/stage_01_data_ingestion.py
saleStorePredictor/pipeline/stage_02_data_validation.py
saleStorePredictor/pipeline/stage_03_data_preprocessing.py
saleStorePredictor/pipeline/stage_04_model_training.py
saleStorePredictor/pipeline/stage_05_model_evaluation.py
saleStorePredictor/utils/__init__.py
saleStorePredictor/utils/common.py
storesSalePrediction-0.0.0.dist-info/LICENSE
storesSalePrediction-0.0.0.dist-info/METADATA
storesSalePrediction-0.0.0.dist-info/WHEEL
storesSalePrediction-0.0.0.dist-info/top_level.txt
storesSalePrediction-0.0.0.dist-info/RECORD
