Metadata-Version: 2.1
Name: storesSalePrediction
Version: 0.0.0
Summary: Package for Store Sale prediction
Home-page: https://github.com/ganpat09/stores_sales_prediction
Author: ganpat09
Author-email: ganpat.choudhary.1994@gmail.com
License: MIT
Project-URL: Bug Tracker, https://github.com/ganpat09/stores_sales_prediction/issues
Classifier: Programming Language :: Python :: 3.8
Classifier: Operating System :: OS Independent
Requires-Python: >=3.7
License-File: LICENSE
Requires-Dist: ensure (==1.0.2)
Provides-Extra: testing
Requires-Dist: pytest (>=7.1.3) ; extra == 'testing'
Requires-Dist: mypy (>=0.971) ; extra == 'testing'
Requires-Dist: flake8 (>=5.0.4) ; extra == 'testing'
Requires-Dist: tox (>=3.25.1) ; extra == 'testing'
Requires-Dist: black (>=22.8.0) ; extra == 'testing'
